{
  "nldates-obsidian": {
    "0.3.0": 122,
    "0.2.6": 233,
    "0.2.5": 101,
    "0.2.4": 121,
    "0.2.3": 90,
    "downloads": 667
  },
  "hotkeysplus-obsidian": {
    "0.2.1": 230,
    "downloads": 230
  },
  "obsidian-git": {
    "1.4.0": 732,
    "1.3.0": 23,
    "1.2.0": 25,
    "v1.2.0": 2,
    "1.1.0": 34,
    "downloads": 816
  },
  "url-into-selection": {
    "1.1.0": 77,
    "1.0.0": 674,
    "downloads": 751
  },
  "sliding-panes-obsidian": {
    "3.1.1": 326,
    "3.1.0": 68,
    "3.0.2": 721,
    "v3.0.1": 735,
    "downloads": 1850
  },
  "cm-show-whitespace-obsidian": {
    "v0.2.0": 72,
    "0.1.0": 320,
    "v0.0.3": 29,
    "v0.0.2": 16,
    "downloads": 437
  },
  "table-editor-obsidian": {
    "0.5.6": 364,
    "0.5.5": 432,
    "0.5.4": 290,
    "0.5.3": 96,
    "0.5.2": 369,
    "0.5.0": 26,
    "0.4.2": 285,
    "0.4.1": 22,
    "0.4.0": 96,
    "0.3.2": 67,
    "0.2.1": 37,
    "0.2.0": 10,
    "downloads": 2094
  },
  "note-refactor-obsidian": {
    "1.4.7": 153,
    "1.4.6": 262,
    "1.4.5": 322,
    "1.4.4": 44,
    "1.4.2": 18,
    "1.4.1": 1,
    "1.3.0": 7,
    "1.2.8": 16,
    "1.2.6": 1,
    "1.2.5": 2,
    "1.2.4": 1,
    "1.2.3": 1,
    "1.2.2": 12,
    "1.2.1": 3,
    "1.2.0": 4,
    "1.1.5": 63,
    "1.1.4": 1,
    "1.1.3": 1,
    "downloads": 912
  },
  "calendar": {
    "1.2.5": 21,
    "1.2.3": 439,
    "1.2.2": 106,
    "1.2.1": 1,
    "1.2.0": 1336,
    "1.1.8": 555,
    "1.1.7": 241,
    "1.1.6": 12,
    "1.1.5": 52,
    "1.1.4": 3,
    "1.1.3": 55,
    "1.1.2": 18,
    "1.1.0": 53,
    "1.0.3": 120,
    "1.0.2": 12,
    "1.0.1": 8,
    "downloads": 3032
  },
  "mrj-text-expand": {
    "0.5.1": 77,
    "0.5.0": 24,
    "0.4.0": 183,
    "downloads": 284
  },
  "mrj-jump-to-link": {
    "0.0.3": 123,
    "downloads": 123
  },
  "mrj-backlinks-in-document": {
    "0.0.1": 603,
    "downloads": 603
  },
  "obsidian-reading-time": {
    "1.0.4": 277,
    "1.0.3": 57,
    "1.0.2": 3,
    "1.0.1": 250,
    "downloads": 587
  },
  "todoist-sync-plugin": {
    "1.5.0": 269,
    "downloads": 269
  },
  "obsidian-vimrc-support": {
    "0.1.1": 30,
    "0.1.0": 93,
    "downloads": 123
  },
  "shortcuts-extender": {
    "1.0.3": 19,
    "1.0.2": 23,
    "1.0.1": 16,
    "1.0.0": 23,
    "downloads": 81
  },
  "mrj-crosslink-between-notes": {
    "0.0.1": 149,
    "downloads": 149
  },
  "darlal-switcher-plus": {
    "0.0.6": 181,
    "downloads": 181
  },
  "obsidian-day-planner": {
    "0.3.3": 100,
    "0.3.2": 65,
    "0.2.4": 56,
    "0.2.3": 106,
    "0.2.2": 36,
    "0.2.1": 3,
    "0.2.0": 1,
    "0.1.8": 9,
    "0.1.7": 1,
    "0.1.6": 1,
    "0.1.5": 13,
    "0.1.0": 116,
    "downloads": 507
  },
  "cm-editor-syntax-highlight-obsidian": {
    "0.1.1": 306,
    "0.1.0": 3,
    "0.0.1": 302,
    "downloads": 611
  },
  "review-obsidian": {
    "1.3.0": 147,
    "1.2.1": 79,
    "1.2.0": 40,
    "1.1.0": 3,
    "1.0.1": 2,
    "downloads": 271
  },
  "obsidian-discordrpc": {
    "1.3.2": 3,
    "1.2.0": 52,
    "1.1.0": 5,
    "1.0.2": 9,
    "1.0.1": 3,
    "downloads": 72
  },
  "templater-obsidian": {
    "0.3.4": 183,
    "0.3.3": 15,
    "0.3.2": 55,
    "0.3.1": 3,
    "0.3.0": 10,
    "0.2.1": 24,
    "0.2.0": 17,
    "0.1.1": 3,
    "0.1.0": 13,
    "downloads": 323
  },
  "convert-url-to-iframe": {
    "0.1.0": 162,
    "downloads": 162
  },
  "code-block-copy": {
    "0.2.0": 244,
    "0.1.0": 48,
    "downloads": 292
  },
  "searchpp": {
    "0.0.1": 73,
    "downloads": 73
  },
  "better-word-count": {
    "0.3.3": 11,
    "0.3.2": 2,
    "0.3.1": 3,
    "0.3.0": 29,
    "0.2.1": 21,
    "downloads": 66
  },
  "workbench-obsidian": {
    "1.4.0": 39,
    "1.3.1": 35,
    "1.3.0": 77,
    "1.2.0": 10,
    "1.0.0": 1,
    "downloads": 162
  },
  "obsidian-latex-environments": {
    "0.1.0": 50,
    "downloads": 50
  },
  "obsidian-rtl": {
    "0.0.1": 26,
    "downloads": 26
  },
  "markdown-prettifier": {
    "0.0.1": 99,
    "downloads": 99
  },
  "css-snippets": {
    "0.1.2": 15,
    "0.1.0": 2,
    "downloads": 17
  },
  "obsidian-link-indexer": {},
  "macOS-keyboard-nav-obsidian": {
    "1.1.0": 6,
    "1.0.0": 1,
    "downloads": 7
  }
}